pycoffer/__init__.py
pycoffer/config.py
pycoffer/main.py
pycoffer/main_cli.py
pycoffer/main_lib.py
pycoffer/main_static.py
pycoffer/coffers/__init__.py
pycoffer/coffers/bank.py
pycoffer/coffers/market.py
pycoffer/coffers/null.py
pycoffer/coffers/store.py
pycoffer/plugins/__init__.py
pycoffer/plugins/crypt.py
pycoffer/plugins/crypt_cli.py
pycoffer/plugins/password.py
pycoffer/plugins/password_cli.py
pycoffer/plugins/rsync.py
pycoffer/plugins/rsync_cli.py
pycoffer-0.1.4.dist-info/METADATA
pycoffer-0.1.4.dist-info/WHEEL
pycoffer-0.1.4.dist-info/entry_points.txt
pycoffer-0.1.4.dist-info/licenses/LICENSE
pycoffer-0.1.4.dist-info/RECORD
